awscdk_resources_mongodbatlas/__init__.py
awscdk_resources_mongodbatlas/py.typed
awscdk_resources_mongodbatlas/_jsii/__init__.py
awscdk_resources_mongodbatlas/_jsii/awscdk-resources-mongodbatlas@3.13.1.jsii.tgz
awscdk_resources_mongodbatlas-3.13.1.dist-info/LICENSE
awscdk_resources_mongodbatlas-3.13.1.dist-info/METADATA
awscdk_resources_mongodbatlas-3.13.1.dist-info/WHEEL
awscdk_resources_mongodbatlas-3.13.1.dist-info/top_level.txt
awscdk_resources_mongodbatlas-3.13.1.dist-info/RECORD
