Metadata-Version: 2.1
Name: awscdk_resources_mongodbatlas
Version: 3.13.1
Summary: MongoDB Atlas CDK Construct Library for AWS CloudFormation Resources
Home-page: https://github.com/mongodb/awscdk-resources-mongodbatlas.git
Author: MongoDB
License: Apache-2.0
Project-URL: Source, https://github.com/mongodb/awscdk-resources-mongodbatlas.git
Classifier: Intended Audience :: Developers
Classifier: Operating System :: OS Independent
Classifier: Programming Language :: JavaScript
Classifier: Programming Language :: Python :: 3 :: Only
Classifier: Programming Language :: Python :: 3.9
Classifier: Programming Language :: Python :: 3.10
Classifier: Programming Language :: Python :: 3.11
Classifier: Typing :: Typed
Classifier: Development Status :: 5 - Production/Stable
Classifier: License :: OSI Approved
Requires-Python: ~=3.9
License-File: LICENSE
Requires-Dist: aws-cdk-lib <3.0.0,>=2.200.1
Requires-Dist: constructs <11.0.0,>=10.0.5
Requires-Dist: jsii <2.0.0,>=1.118.0
Requires-Dist: publication >=0.0.3
Requires-Dist: typeguard <4.3.0,>=2.13.3
